pysurfline/__init__.py
pysurfline/api/__init__.py
pysurfline/api/client.py
pysurfline/api/models/__init__.py
pysurfline/api/models/spots.py
pysurfline/api/objects.py
pysurfline/api/public.py
pysurfline/api/services.py
pysurfline/core.py
pysurfline/reports.py
pysurfline/utils.py
pysurfline-0.2.1.dist-info/LICENSE
pysurfline-0.2.1.dist-info/METADATA
pysurfline-0.2.1.dist-info/WHEEL
pysurfline-0.2.1.dist-info/RECORD
