Metadata-Version: 2.1
Name: pysurfline
Version: 0.2.1
Summary: python Surfline API
License: MIT
Author: giocaizzi
Author-email: giocaizzi@gmail.com
Requires-Python: >=3.8.1,<4.0.0
Classifier: License :: OSI Approved :: MIT License
Classifier: Programming Language :: Python :: 3
Classifier: Programming Language :: Python :: 3.9
Classifier: Programming Language :: Python :: 3.10
Classifier: Programming Language :: Python :: 3.11
Classifier: Programming Language :: Python :: 3.12
Requires-Dist: matplotlib (<3.8) ; python_version < "3.9"
Requires-Dist: matplotlib (>=3.8,<4.0) ; python_version >= "3.9" and python_version < "4.0"
Requires-Dist: pandas (<2.1) ; python_version < "3.9"
Requires-Dist: pandas (>=2.1,<3.0) ; python_version >= "3.9" and python_version < "4.0"
Requires-Dist: requests (>=2.32.3,<3.0.0)
Project-URL: Documentation, https://giocaizzi.github.io/pysurfline/
Project-URL: Homepage, https://github.com/giocaizzi/pysurfline
Project-URL: Issues, https://github.com/giocaizzi/pysurfline/issues
Project-URL: Repository, https://github.com/giocaizzi/pysurfline
